logger_setup/__init__.py
logger_setup/crashlogger.py
logger_setup/logger_setup.py
logger_setup-0.17.dist-info/LICENSE
logger_setup-0.17.dist-info/METADATA
logger_setup-0.17.dist-info/WHEEL
logger_setup-0.17.dist-info/top_level.txt
logger_setup-0.17.dist-info/RECORD
